{
  "mode": "pre",
  "tag": "beta",
  "initialVersions": {
    "evalite": "0.19.0",
    "evalite-docs": "0.0.1",
    "evalite-tests": "0.0.11",
    "example": "0.0.11"
  },
  "changesets": [
    "0000-cache-config",
    "0000-cache-debug-mode",
    "0000-config-errors",
    "0000-export-command-change",
    "0000-in-memory-default",
    "0000-levenshtein-scorer",
    "0000-optional-scorer-name",
    "0000-phase-ii-server-lifecycle",
    "0000-remove-implicit-vitest-config",
    "0000-remove-streaming",
    "0000-rerun-button",
    "0000-variant-only",
    "0234-auto-dotenv-support",
    "angry-dogs-sort",
    "better-tires-battle",
    "cyan-lines-peel",
    "easy-islands-beam",
    "every-candles-press",
    "fast-bugs-wash",
    "fruity-pigs-burn",
    "late-dryers-repair",
    "lemon-things-show",
    "long-olives-give",
    "mighty-tires-type",
    "quiet-ears-spend",
    "rare-ties-worry",
    "real-phones-join",
    "salty-boxes-talk",
    "sixty-jeans-melt",
    "spicy-islands-heal",
    "table-rendering",
    "tasty-parents-bathe",
    "thick-birds-design",
    "wet-clocks-camp"
  ]
}
